pkg/__init__.py
pkg/config.json
vuln_common-0.0.3.dist-info/METADATA
vuln_common-0.0.3.dist-info/WHEEL
vuln_common-0.0.3.dist-info/top_level.txt
vuln_common-0.0.3.dist-info/RECORD
