Metadata-Version: 2.1
Name: vuln-common
Version: 0.0.3
Summary: Common Utils Pkg for VulnCorp
Home-page: https://github.com/VulnCorp/vuln-common
Author: VulnCorp
Author-email: admin@vulncorp.com
License: UNKNOWN
Project-URL: Bug Tracker, https://github.com/VulnCorp/vuln-common/issues
Platform: UNKNOWN
Classifier: Programming Language :: Python :: 3
Classifier: License :: OSI Approved :: MIT License
Classifier: Operating System :: OS Independent
Requires-Python: >=3.6
